{
  "Title": "Sample",
  "topic": "Social",
  "Questions": [
    {
      "QuestionID":1,
      "Question": "Capital of India",
      "Options": ["Delhi", "Chennai", "Mumbai", "Kolkata"],
      "type": "MCQ",
      "Answer": "A",
      "Difficulty": "1",
      "Priority": "2"
    },
    {
      "QuestionID":2,
      "Question": "Capital of TamilNadu",
      "Options": ["Madurai", "Chennai", "Trichy", "Erode"],
      "type": "MCQ",
      "Answer": "Chennai",
      "Difficulty": "1",
      "Priority": "2"
    }
  ]
}
